serfio/__init__.py
serfio/codec.py
serfio/errors.py
serfio/protocol.py
serfio/serf.py
serfio/transport.py
serfio-0.3.3.dist-info/LICENSE
serfio-0.3.3.dist-info/METADATA
serfio-0.3.3.dist-info/WHEEL
serfio-0.3.3.dist-info/top_level.txt
serfio-0.3.3.dist-info/RECORD
