Metadata-Version: 2.1
Name: serfio
Version: 0.3.3
Summary: Python interface to Serf
Author-email: Andrey Gubarev <andrey@andreygubarev.com>
License: MIT
Project-URL: Homepage, https://github.com/andreygubarev/python-serfio/
License-File: LICENSE
Requires-Dist: msgpack >=1.0.3
